{"nodes": [{"id": "c_users_omagrawal_downloads_dashboardaistudio_lib_features_ts", "label": "features.ts", "file_type": "code", "source_file": "C:\\Users\\OmAgrawal\\Downloads\\dashboardaistudio\\lib\\features.ts", "source_location": "L1"}, {"id": "features_getdefaultfeatures", "label": "getDefaultFeatures()", "file_type": "code", "source_file": "C:\\Users\\OmAgrawal\\Downloads\\dashboardaistudio\\lib\\features.ts", "source_location": "L91"}, {"id": "features_featuresfromplan", "label": "featuresFromPlan()", "file_type": "code", "source_file": "C:\\Users\\OmAgrawal\\Downloads\\dashboardaistudio\\lib\\features.ts", "source_location": "L98"}, {"id": "features_trialdaysleft", "label": "trialDaysLeft()", "file_type": "code", "source_file": "C:\\Users\\OmAgrawal\\Downloads\\dashboardaistudio\\lib\\features.ts", "source_location": "L106"}], "edges": [{"source": "c_users_omagrawal_downloads_dashboardaistudio_lib_features_ts", "target": "features_getdefaultfeatures", "relation": "contains", "confidence": "EXTRACTED", "source_file": "C:\\Users\\OmAgrawal\\Downloads\\dashboardaistudio\\lib\\features.ts", "source_location": "L91", "weight": 1.0}, {"source": "c_users_omagrawal_downloads_dashboardaistudio_lib_features_ts", "target": "features_featuresfromplan", "relation": "contains", "confidence": "EXTRACTED", "source_file": "C:\\Users\\OmAgrawal\\Downloads\\dashboardaistudio\\lib\\features.ts", "source_location": "L98", "weight": 1.0}, {"source": "c_users_omagrawal_downloads_dashboardaistudio_lib_features_ts", "target": "features_trialdaysleft", "relation": "contains", "confidence": "EXTRACTED", "source_file": "C:\\Users\\OmAgrawal\\Downloads\\dashboardaistudio\\lib\\features.ts", "source_location": "L106", "weight": 1.0}], "raw_calls": [{"caller_nid": "features_getdefaultfeatures", "callee": "reduce", "source_file": "C:\\Users\\OmAgrawal\\Downloads\\dashboardaistudio\\lib\\features.ts", "source_location": "L92"}, {"caller_nid": "features_getdefaultfeatures", "callee": "values", "source_file": "C:\\Users\\OmAgrawal\\Downloads\\dashboardaistudio\\lib\\features.ts", "source_location": "L92"}, {"caller_nid": "features_featuresfromplan", "callee": "reduce", "source_file": "C:\\Users\\OmAgrawal\\Downloads\\dashboardaistudio\\lib\\features.ts", "source_location": "L100"}, {"caller_nid": "features_featuresfromplan", "callee": "values", "source_file": "C:\\Users\\OmAgrawal\\Downloads\\dashboardaistudio\\lib\\features.ts", "source_location": "L100"}, {"caller_nid": "features_trialdaysleft", "callee": "toDate", "source_file": "C:\\Users\\OmAgrawal\\Downloads\\dashboardaistudio\\lib\\features.ts", "source_location": "L108"}, {"caller_nid": "features_trialdaysleft", "callee": "ceil", "source_file": "C:\\Users\\OmAgrawal\\Downloads\\dashboardaistudio\\lib\\features.ts", "source_location": "L109"}, {"caller_nid": "features_trialdaysleft", "callee": "getTime", "source_file": "C:\\Users\\OmAgrawal\\Downloads\\dashboardaistudio\\lib\\features.ts", "source_location": "L109"}, {"caller_nid": "features_trialdaysleft", "callee": "now", "source_file": "C:\\Users\\OmAgrawal\\Downloads\\dashboardaistudio\\lib\\features.ts", "source_location": "L109"}]}