{"nodes": [{"id": "app_team_page_tsx", "label": "page.tsx", "file_type": "code", "source_file": "app\\team\\page.tsx", "source_location": "L1"}, {"id": "page_sendrolenotification", "label": "sendRoleNotification()", "file_type": "code", "source_file": "app\\team\\page.tsx", "source_location": "L48"}, {"id": "page_handleinvite", "label": "handleInvite()", "file_type": "code", "source_file": "app\\team\\page.tsx", "source_location": "L60"}, {"id": "page_handlerevokeinvite", "label": "handleRevokeInvite()", "file_type": "code", "source_file": "app\\team\\page.tsx", "source_location": "L101"}, {"id": "page_handlerolechange", "label": "handleRoleChange()", "file_type": "code", "source_file": "app\\team\\page.tsx", "source_location": "L109"}, {"id": "page_handletoggleassignment", "label": "handleToggleAssignment()", "file_type": "code", "source_file": "app\\team\\page.tsx", "source_location": "L119"}, {"id": "page_handleremovemember", "label": "handleRemoveMember()", "file_type": "code", "source_file": "app\\team\\page.tsx", "source_location": "L128"}], "edges": [{"source": "app_team_page_tsx", "target": "authprovider", "relation": "imports_from", "confidence": "EXTRACTED", "source_file": "app\\team\\page.tsx", "source_location": "L3", "weight": 1.0}, {"source": "app_team_page_tsx", "target": "sidebar", "relation": "imports_from", "confidence": "EXTRACTED", "source_file": "app\\team\\page.tsx", "source_location": "L4", "weight": 1.0}, {"source": "app_team_page_tsx", "target": "header", "relation": "imports_from", "confidence": "EXTRACTED", "source_file": "app\\team\\page.tsx", "source_location": "L5", "weight": 1.0}, {"source": "app_team_page_tsx", "target": "react", "relation": "imports_from", "confidence": "EXTRACTED", "source_file": "app\\team\\page.tsx", "source_location": "L6", "weight": 1.0}, {"source": "app_team_page_tsx", "target": "firestore", "relation": "imports_from", "confidence": "EXTRACTED", "source_file": "app\\team\\page.tsx", "source_location": "L7", "weight": 1.0}, {"source": "app_team_page_tsx", "target": "firebase", "relation": "imports_from", "confidence": "EXTRACTED", "source_file": "app\\team\\page.tsx", "source_location": "L11", "weight": 1.0}, {"source": "app_team_page_tsx", "target": "lucide_react", "relation": "imports_from", "confidence": "EXTRACTED", "source_file": "app\\team\\page.tsx", "source_location": "L12", "weight": 1.0}, {"source": "app_team_page_tsx", "target": "page_sendrolenotification", "relation": "contains", "confidence": "EXTRACTED", "source_file": "app\\team\\page.tsx", "source_location": "L48", "weight": 1.0}, {"source": "app_team_page_tsx", "target": "page_handleinvite", "relation": "contains", "confidence": "EXTRACTED", "source_file": "app\\team\\page.tsx", "source_location": "L60", "weight": 1.0}, {"source": "app_team_page_tsx", "target": "page_handlerevokeinvite", "relation": "contains", "confidence": "EXTRACTED", "source_file": "app\\team\\page.tsx", "source_location": "L101", "weight": 1.0}, {"source": "app_team_page_tsx", "target": "page_handlerolechange", "relation": "contains", "confidence": "EXTRACTED", "source_file": "app\\team\\page.tsx", "source_location": "L109", "weight": 1.0}, {"source": "app_team_page_tsx", "target": "page_handletoggleassignment", "relation": "contains", "confidence": "EXTRACTED", "source_file": "app\\team\\page.tsx", "source_location": "L119", "weight": 1.0}, {"source": "app_team_page_tsx", "target": "page_handleremovemember", "relation": "contains", "confidence": "EXTRACTED", "source_file": "app\\team\\page.tsx", "source_location": "L128", "weight": 1.0}, {"source": "page_handleinvite", "target": "page_sendrolenotification", "relation": "calls", "confidence": "EXTRACTED", "source_file": "app\\team\\page.tsx", "source_location": "L84", "weight": 1.0}, {"source": "page_handlerolechange", "target": "page_sendrolenotification", "relation": "calls", "confidence": "EXTRACTED", "source_file": "app\\team\\page.tsx", "source_location": "L113", "weight": 1.0}, {"source": "page_handleremovemember", "target": "page_sendrolenotification", "relation": "calls", "confidence": "EXTRACTED", "source_file": "app\\team\\page.tsx", "source_location": "L133", "weight": 1.0}], "raw_calls": [{"caller_nid": "page_sendrolenotification", "callee": "fetch", "source_file": "app\\team\\page.tsx", "source_location": "L50"}, {"caller_nid": "page_sendrolenotification", "callee": "stringify", "source_file": "app\\team\\page.tsx", "source_location": "L53"}, {"caller_nid": "page_sendrolenotification", "callee": "error", "source_file": "app\\team\\page.tsx", "source_location": "L56"}, {"caller_nid": "page_handleinvite", "callee": "preventDefault", "source_file": "app\\team\\page.tsx", "source_location": "L61"}, {"caller_nid": "page_handleinvite", "callee": "trim", "source_file": "app\\team\\page.tsx", "source_location": "L62"}, {"caller_nid": "page_handleinvite", "callee": "setIsInviting", "source_file": "app\\team\\page.tsx", "source_location": "L64"}, {"caller_nid": "page_handleinvite", "callee": "setError", "source_file": "app\\team\\page.tsx", "source_location": "L65"}, {"caller_nid": "page_handleinvite", "callee": "setSuccess", "source_file": "app\\team\\page.tsx", "source_location": "L66"}, {"caller_nid": "page_handleinvite", "callee": "some", "source_file": "app\\team\\page.tsx", "source_location": "L69"}, {"caller_nid": "page_handleinvite", "callee": "some", "source_file": "app\\team\\page.tsx", "source_location": "L72"}, {"caller_nid": "page_handleinvite", "callee": "addDoc", "source_file": "app\\team\\page.tsx", "source_location": "L76"}, {"caller_nid": "page_handleinvite", "callee": "collection", "source_file": "app\\team\\page.tsx", "source_location": "L76"}, {"caller_nid": "page_handleinvite", "callee": "trim", "source_file": "app\\team\\page.tsx", "source_location": "L77"}, {"caller_nid": "page_handleinvite", "callee": "serverTimestamp", "source_file": "app\\team\\page.tsx", "source_location": "L80"}, {"caller_nid": "page_handleinvite", "callee": "trim", "source_file": "app\\team\\page.tsx", "source_location": "L85"}, {"caller_nid": "page_handleinvite", "callee": "split", "source_file": "app\\team\\page.tsx", "source_location": "L86"}, {"caller_nid": "page_handleinvite", "callee": "setSuccess", "source_file": "app\\team\\page.tsx", "source_location": "L91"}, {"caller_nid": "page_handleinvite", "callee": "setInviteEmail", "source_file": "app\\team\\page.tsx", "source_location": "L92"}, {"caller_nid": "page_handleinvite", "callee": "setInviteRole", "source_file": "app\\team\\page.tsx", "source_location": "L93"}, {"caller_nid": "page_handleinvite", "callee": "setError", "source_file": "app\\team\\page.tsx", "source_location": "L95"}, {"caller_nid": "page_handleinvite", "callee": "setIsInviting", "source_file": "app\\team\\page.tsx", "source_location": "L97"}, {"caller_nid": "page_handlerevokeinvite", "callee": "deleteDoc", "source_file": "app\\team\\page.tsx", "source_location": "L103"}, {"caller_nid": "page_handlerevokeinvite", "callee": "doc", "source_file": "app\\team\\page.tsx", "source_location": "L103"}, {"caller_nid": "page_handlerevokeinvite", "callee": "error", "source_file": "app\\team\\page.tsx", "source_location": "L105"}, {"caller_nid": "page_handlerolechange", "callee": "updateDoc", "source_file": "app\\team\\page.tsx", "source_location": "L112"}, {"caller_nid": "page_handlerolechange", "callee": "doc", "source_file": "app\\team\\page.tsx", "source_location": "L112"}, {"caller_nid": "page_handlerolechange", "callee": "error", "source_file": "app\\team\\page.tsx", "source_location": "L115"}, {"caller_nid": "page_handletoggleassignment", "callee": "updateDoc", "source_file": "app\\team\\page.tsx", "source_location": "L122"}, {"caller_nid": "page_handletoggleassignment", "callee": "doc", "source_file": "app\\team\\page.tsx", "source_location": "L122"}, {"caller_nid": "page_handletoggleassignment", "callee": "error", "source_file": "app\\team\\page.tsx", "source_location": "L124"}, {"caller_nid": "page_handleremovemember", "callee": "confirm", "source_file": "app\\team\\page.tsx", "source_location": "L130"}, {"caller_nid": "page_handleremovemember", "callee": "updateDoc", "source_file": "app\\team\\page.tsx", "source_location": "L132"}, {"caller_nid": "page_handleremovemember", "callee": "doc", "source_file": "app\\team\\page.tsx", "source_location": "L132"}, {"caller_nid": "page_handleremovemember", "callee": "deleteField", "source_file": "app\\team\\page.tsx", "source_location": "L132"}, {"caller_nid": "page_handleremovemember", "callee": "error", "source_file": "app\\team\\page.tsx", "source_location": "L135"}]}